bcd_counter.v
/*
 
 */

module bcd_counter (
		    input clock,reset,
		    output tc,
		    output [3:0] q
		    );

   reg [3:0] q = 0;
   reg 	     tc = 0;
   
 
  always @(posedge clock) begin
    if(reset) begin
       q <= 4'd0;
       tc <= 1'b0;
    end
    else begin
      q = q+1;
      if(q == 4'd10) begin
	 q <= 4'd0;
	 tc <= 1'b1;
      end
      else tc <= 1'b0;
    end
  end

endmodule // bcd_counter

bcd_8bit_counter.v
/**************************************
* Module: bcd_8bit_counter
* Date:2018-04-29  
* Author: sladekm     
*
* Description: 
***************************************/
module  bcd_8bit_counter(
    input   clk,
    input   reset,
    output  [3:0] bcd0,
    output  [3:0] bcd1
);
   wire 	  tc;
   wire 	  tc1;
   
   bcd_counter c0(.clock(clk), .reset(reset),.tc(tc),.q(bcd0));
   bcd_counter c1(.clock(tc), .reset(reset), .tc(tc1),.q(bcd1));
   
endmodule

bcd_8bit_counter_tb.v
/*
 Test bench
*/

`timescale 1ns/10ps

module bcd_8bit_counter_tb();
   reg clr, clk;
   wire  tc;
   wire [3:0] q0;
   wire [3:0] q1;
   
   bcd_8bit_counter dut(clk, clr, q0, q1);

   initial begin
      $dumpfile ("bcd_8bit_counter.vcd");
      $dumpvars;
   end
   
   initial begin
      clk = 0;
      forever #5 clk = ~clk;
   end
   initial begin
      clr = 1;
      #20;
      clr = 0;
   end
   initial begin
      #500;
      $finish;
   end
   
endmodule // bcd_8bit_counter_tb

bcd_8bit_counter.vcd
$date
	Sun Mar 19 00:47:22 2023
$end
$version
	Icarus Verilog
$end
$timescale
	10ps
$end
$scope module bcd_8bit_counter_tb $end
$var wire 4 ! q1 [3:0] $end
$var wire 4 " q0 [3:0] $end
$var reg 1 # clk $end
$var reg 1 $ clr $end
$scope module dut $end
$var wire 1 # clk $end
$var wire 1 $ reset $end
$var wire 1 % tc1 $end
$var wire 1 & tc $end
$var wire 4 ' bcd1 [3:0] $end
$var wire 4 ( bcd0 [3:0] $end
$scope module c0 $end
$var wire 1 # clock $end
$var wire 1 $ reset $end
$var reg 4 ) q [3:0] $end
$var reg 1 & tc $end
$upscope $end
$scope module c1 $end
$var wire 1 & clock $end
$var wire 1 $ reset $end
$var reg 4 * q [3:0] $end
$var reg 1 % tc $end
$upscope $end
$upscope $end
$upscope $end
$enddefinitions $end
#0
$dumpvars
b0 *
b0 )
b0 (
b0 '
0&
0%
1$
0#
b0 "
b0 !
$end
#500
1#
#1000
0#
#1500
1#
#2000
0#
0$
#2500
b1 "
b1 (
b1 )
1#
#3000
0#
#3500
b10 "
b10 (
b10 )
1#
#4000
0#
#4500
b11 "
b11 (
b11 )
1#
#5000
0#
#5500
b100 "
b100 (
b100 )
1#
#6000
0#
#6500
b101 "
b101 (
b101 )
1#
#7000
0#
#7500
b110 "
b110 (
b110 )
1#
#8000
0#
#8500
b111 "
b111 (
b111 )
1#
#9000
0#
#9500
b1000 "
b1000 (
b1000 )
1#
#10000
0#
#10500
b1001 "
b1001 (
b1001 )
1#
#11000
0#
#11500
b1 !
b1 '
b1 *
1&
b0 "
b0 (
b0 )
1#
#12000
0#
#12500
0&
b1 "
b1 (
b1 )
1#
#13000
0#
#13500
b10 "
b10 (
b10 )
1#
#14000
0#
#14500
b11 "
b11 (
b11 )
1#
#15000
0#
#15500
b100 "
b100 (
b100 )
1#
#16000
0#
#16500
b101 "
b101 (
b101 )
1#
#17000
0#
#17500
b110 "
b110 (
b110 )
1#
#18000
0#
#18500
b111 "
b111 (
b111 )
1#
#19000
0#
#19500
b1000 "
b1000 (
b1000 )
1#
#20000
0#
#20500
b1001 "
b1001 (
b1001 )
1#
#21000
0#
#21500
b10 !
b10 '
b10 *
1&
b0 "
b0 (
b0 )
1#
#22000
0#
#22500
0&
b1 "
b1 (
b1 )
1#
#23000
0#
#23500
b10 "
b10 (
b10 )
1#
#24000
0#
#24500
b11 "
b11 (
b11 )
1#
#25000
0#
#25500
b100 "
b100 (
b100 )
1#
#26000
0#
#26500
b101 "
b101 (
b101 )
1#
#27000
0#
#27500
b110 "
b110 (
b110 )
1#
#28000
0#
#28500
b111 "
b111 (
b111 )
1#
#29000
0#
#29500
b1000 "
b1000 (
b1000 )
1#
#30000
0#
#30500
b1001 "
b1001 (
b1001 )
1#
#31000
0#
#31500
b11 !
b11 '
b11 *
1&
b0 "
b0 (
b0 )
1#
#32000
0#
#32500
0&
b1 "
b1 (
b1 )
1#
#33000
0#
#33500
b10 "
b10 (
b10 )
1#
#34000
0#
#34500
b11 "
b11 (
b11 )
1#
#35000
0#
#35500
b100 "
b100 (
b100 )
1#
#36000
0#
#36500
b101 "
b101 (
b101 )
1#
#37000
0#
#37500
b110 "
b110 (
b110 )
1#
#38000
0#
#38500
b111 "
b111 (
b111 )
1#
#39000
0#
#39500
b1000 "
b1000 (
b1000 )
1#
#40000
0#
#40500
b1001 "
b1001 (
b1001 )
1#
#41000
0#
#41500
b100 !
b100 '
b100 *
1&
b0 "
b0 (
b0 )
1#
#42000
0#
#42500
0&
b1 "
b1 (
b1 )
1#
#43000
0#
#43500
b10 "
b10 (
b10 )
1#
#44000
0#
#44500
b11 "
b11 (
b11 )
1#
#45000
0#
#45500
b100 "
b100 (
b100 )
1#
#46000
0#
#46500
b101 "
b101 (
b101 )
1#
#47000
0#
#47500
b110 "
b110 (
b110 )
1#
#48000
0#
#48500
b111 "
b111 (
b111 )
1#
#49000
0#
#49500
b1000 "
b1000 (
b1000 )
1#
