definitions.v
/**************************************
* Module: definitions
* Date:2018-02-24  
* Author: sladekm     
*
* Description: 
***************************************/
`define H_PULSE     96      // H-SYNC pulse width 96 * 40 ns (25 Mhz) = 3.84 uS
`define H_BP        48      // H-BP back porch pulse width
`define H_PIXELS    640     // H-PIX Number of pixels horisontally
`define H_FP        16      // H-FP front porch pulse width
`define H_POL       1'b0    // H-SYNC polarity
`define H_FRAME     800     // 800 = 96 (H-SYNC) + 48 (H-BP) + 640 (H-PIX) + 16 (H-FP)

`define V_PULSE     2       // V-SYNC pulse width
`define V_BP        33      // V-BP back porch pulse width
`define V_PIXELS    480     // V-PIX Number of pixels vertically
`define V_FP        10      // V-FP front porch pulse width
`define V_POL       1'b1    // V-SYNC polarity
`define V_FRAME     525     // 525 = 2 (V-SYNC) + 33 (V-BP) + 480 (V-PIX) + 10 (V-FP)

`define LEFT_BORDER     0
`define RIGHT_BORDER    `H_PIXELS - 1
`define TOP_BORDER      0
`define BOTTOM_BORDER   `V_PIXELS - 1

`define COLOR_BORDER    {3'd7,3'd0,3'd0} // Border color
`define COLOR_BLACK     {3'd0,3'd0,3'd0} // Black color   
`define COLOR_BALL      {3'd0,3'd0,3'd7} // Ball color
`define COLOR_PADDLE    {3'd0,3'd7,3'd0} // Paddle color
`define COLOR_WHITE     {3'd7,3'd7,3'd7} // Osd color

`define BALL_SIZE       16   // Size of the ball. Both x and y are the same

`define PADDLE_WIDTH    64      // Paddle width
`define PADDLE_HEIGHT   12      // Paddle height
`define PADDLE_TOP_Y    460     // Initial y position of top side of a paddle
`define MAX_PADDLE_X  `H_PIXELS - `PADDLE_WIDTH-3
`define MIN_PADDLE_X  2

`define CHARACTER_SIZE      24       // Total number of horizontal lines per character
`define CHARACTER_SEGMENTS  8       // Number of horizontal segment per character
`define CHARACTER_LINE_SIZE 3       // Number of horizontal lines per one charcter segment line
`define CHAR_BUF_SIZE       10       // Size of the character buffer

osd_time_base.v
/**************************************
* Module: osd_time_base
* Date:2018-04-28  
* Author: sladekm     
*
* Description: 
***************************************/
`include    "definitions.v"
module  osd_time_base(
    input   clk,
    input   start,
    input   enable,
    output  clk_out1,
    output  clk_out2
);

reg     [3:0]   pos_count = 4'b0;
 
always @(posedge clk) begin
    if (start) pos_count <= 0;
    else if(pos_count == `CHARACTER_SEGMENTS-1) pos_count <= 0;
    else pos_count <= pos_count +1;
end

assign clk_out1 = (pos_count == 1) & enable;
assign clk_out2 = (pos_count == 5) & enable;

endmodule

osd_time_base_tb.v
/*
 Test bench
*/

`timescale 1ns/10ps

module osd_time_base_tb();
   reg clk;
   reg start = 1'b1;
   
   
   osd_time_base dut(.clk(clk), .start(start), .enable(1'b1), .clk_out1(clk1), .clk_out2(clk2));

   initial begin
      $dumpfile ("osd_time_base.vcd");
      $dumpvars;
   end
   initial begin
      clk = 0;
      forever #5 clk = ~clk;
   end
   initial begin
      #10;
      start = 1'b0;
   end	
   initial begin
      #500;
      $finish;
   end
   
endmodule // osd_time_base_tb

osd_time_base.vcd
$date
	Sun Mar 19 20:57:00 2023
$end
$version
	Icarus Verilog
$end
$timescale
	10ps
$end
$scope module osd_time_base_tb $end
$var wire 1 ! clk2 $end
$var wire 1 " clk1 $end
$var reg 1 # clk $end
$var reg 1 $ start $end
$scope module dut $end
$var wire 1 # clk $end
$var wire 1 " clk_out1 $end
$var wire 1 ! clk_out2 $end
$var wire 1 % enable $end
$var wire 1 $ start $end
$var reg 4 & pos_count [3:0] $end
$upscope $end
$upscope $end
$enddefinitions $end
#0
$dumpvars
b0 &
1%
1$
0#
0"
0!
$end
#500
1#
#1000
0#
0$
#1500
1"
b1 &
1#
#2000
0#
#2500
0"
b10 &
1#
#3000
0#
#3500
b11 &
1#
#4000
0#
#4500
b100 &
1#
#5000
0#
#5500
1!
b101 &
1#
#6000
0#
#6500
0!
b110 &
1#
#7000
0#
#7500
b111 &
1#
#8000
0#
#8500
b0 &
1#
#9000
0#
#9500
1"
b1 &
1#
#10000
0#
#10500
0"
b10 &
1#
#11000
0#
#11500
b11 &
1#
#12000
0#
#12500
b100 &
1#
#13000
0#
#13500
1!
b101 &
1#
#14000
0#
#14500
0!
b110 &
1#
#15000
0#
#15500
b111 &
1#
#16000
0#
#16500
b0 &
1#
#17000
0#
#17500
1"
b1 &
1#
#18000
0#
#18500
0"
b10 &
1#
#19000
0#
#19500
b11 &
1#
#20000
0#
#20500
b100 &
1#
#21000
0#
#21500
1!
b101 &
1#
#22000
0#
#22500
0!
b110 &
1#
#23000
0#
#23500
b111 &
1#
#24000
0#
#24500
b0 &
1#
#25000
0#
#25500
1"
b1 &
1#
#26000
0#
#26500
0"
b10 &
1#
#27000
0#
#27500
b11 &
1#
#28000
0#
#28500
b100 &
1#
#29000
0#
#29500
1!
b101 &
1#
#30000
0#
#30500
0!
b110 &
1#
#31000
0#
#31500
b111 &
1#
#32000
0#
#32500
b0 &
1#
#33000
0#
#33500
1"
b1 &
1#
#34000
0#
#34500
0"
b10 &
1#
#35000
0#
#35500
b11 &
1#
#36000
0#
#36500
b100 &
1#
#37000
0#
#37500
1!
b101 &
1#
#38000
0#
#38500
0!
b110 &
1#
#39000
0#
#39500
b111 &
1#
#40000
0#
#40500
b0 &
1#
#41000
0#
#41500
1"
b1 &
1#
#42000
0#
#42500
0"
b10 &
1#
#43000
0#
#43500
b11 &
1#
#44000
0#
#44500
b100 &
1#
#45000
0#
#45500
1!
b101 &
1#
#46000
0#
#46500
0!
b110 &
1#
#47000
0#
#47500
b111 &
1#
#48000
0#
#48500
b0 &
1#
#49000
0#
#49500
1"
b1 &
1#
